<?xml version="1.0" encoding="UTF-8"?>
<Law Lang="ja" Era="Reiwa" Year="07" Num="039" PromulgateMonth="2" PromulgateDay="21" LawType="CabinetOrder"><LawNum>令和七年政令第三十九号</LawNum><LawBody><LawTitle Kana="しょくりょうきょうきゅうこんなんじたいたいさくほうしこうれい" Abbrev="" AbbrevKana="">食料供給困難事態対策法施行令</LawTitle>
    <EnactStatement>内閣は、食料供給困難事態対策法（令和六年法律第六十一号）第二条第一号、第二号、第六号及び第七号の規定に基づき、この政令を制定する。</EnactStatement>
    <MainProvision>
      <Article Num="1">
        <ArticleCaption>（特定食料）</ArticleCaption>
        <ArticleTitle>第一条</ArticleTitle>
        <Paragraph Num="1">
          <ParagraphNum/>
          <ParagraphSentence>
            <Sentence Num="1" WritingMode="vertical">食料供給困難事態対策法（以下「法」という。）第二条第一号の政令で定める農林水産物は、次に掲げる農林水産物とする。</Sentence>
          </ParagraphSentence>
          <Item Num="1">
            <ItemTitle>一</ItemTitle>
            <ItemSentence>
              <Sentence Num="1" WritingMode="vertical">米穀</Sentence>
            </ItemSentence>
          </Item>
          <Item Num="2">
            <ItemTitle>二</ItemTitle>
            <ItemSentence>
              <Sentence Num="1" WritingMode="vertical">小麦</Sentence>
            </ItemSentence>
          </Item>
          <Item Num="3">
            <ItemTitle>三</ItemTitle>
            <ItemSentence>
              <Sentence Num="1" WritingMode="vertical">大豆</Sentence>
            </ItemSentence>
          </Item>
          <Item Num="4">
            <ItemTitle>四</ItemTitle>
            <ItemSentence>
              <Sentence Num="1" WritingMode="vertical">菜種又は油やしの実</Sentence>
            </ItemSentence>
          </Item>
          <Item Num="5">
            <ItemTitle>五</ItemTitle>
            <ItemSentence>
              <Sentence Num="1" WritingMode="vertical">てん菜又はさとうきび</Sentence>
            </ItemSentence>
          </Item>
          <Item Num="6">
            <ItemTitle>六</ItemTitle>
            <ItemSentence>
              <Sentence Num="1" WritingMode="vertical">生乳（しぼったままの牛乳をいう。）</Sentence>
            </ItemSentence>
          </Item>
          <Item Num="7">
            <ItemTitle>七</ItemTitle>
            <ItemSentence>
              <Sentence Num="1" WritingMode="vertical">牛、豚又は鶏の肉</Sentence>
            </ItemSentence>
          </Item>
          <Item Num="8">
            <ItemTitle>八</ItemTitle>
            <ItemSentence>
              <Sentence Num="1" WritingMode="vertical">鶏卵</Sentence>
            </ItemSentence>
          </Item>
        </Paragraph>
        <Paragraph Num="2">
          <ParagraphNum>２</ParagraphNum>
          <ParagraphSentence>
            <Sentence Num="1" WritingMode="vertical">法第二条第一号の政令で定める食品は、次に掲げる食品とする。</Sentence>
          </ParagraphSentence>
          <Item Num="1">
            <ItemTitle>一</ItemTitle>
            <ItemSentence>
              <Sentence Num="1" WritingMode="vertical">小麦粉</Sentence>
            </ItemSentence>
          </Item>
          <Item Num="2">
            <ItemTitle>二</ItemTitle>
            <ItemSentence>
              <Sentence Num="1" WritingMode="vertical">植物油脂（前項第三号又は第四号に掲げる農林水産物を原材料とするものに限る。）</Sentence>
            </ItemSentence>
          </Item>
          <Item Num="3">
            <ItemTitle>三</ItemTitle>
            <ItemSentence>
              <Sentence Num="1" WritingMode="vertical">砂糖（前項第五号に掲げる農林水産物を原材料とするものに限る。）</Sentence>
            </ItemSentence>
          </Item>
          <Item Num="4">
            <ItemTitle>四</ItemTitle>
            <ItemSentence>
              <Sentence Num="1" WritingMode="vertical">飲用牛乳（加工乳（前項第六号に掲げる農林水産物を原材料とするものに限る。）を含む。）又は乳製品（同号に掲げる農林水産物を原材料とするものに限る。）</Sentence>
            </ItemSentence>
          </Item>
          <Item Num="5">
            <ItemTitle>五</ItemTitle>
            <ItemSentence>
              <Sentence Num="1" WritingMode="vertical">鶏卵から卵殻を取り除いたもの（乾燥その他保存に適する処理をしたものを含む。）</Sentence>
            </ItemSentence>
          </Item>
        </Paragraph>
      </Article>
      <Article Num="2">
        <ArticleCaption>（特定資材）</ArticleCaption>
        <ArticleTitle>第二条</ArticleTitle>
        <Paragraph Num="1">
          <ParagraphNum/>
          <ParagraphSentence>
            <Sentence Num="1" WritingMode="vertical">法第二条第二号の政令で定める資材は、次の各号に掲げる農林水産物の区分に応じ、当該各号に定める資材とする。</Sentence>
          </ParagraphSentence>
          <Item Num="1">
            <ItemTitle>一</ItemTitle>
            <ItemSentence>
              <Column Num="1">
                <Sentence Num="1" WritingMode="vertical">前条第一項第一号から第五号までに掲げる農林水産物</Sentence>
              </Column>
              <Column Num="2">
                <Sentence Num="1" WritingMode="vertical">それぞれ当該農林水産物の生産に用いられる肥料、農薬（農薬取締法（昭和二十三年法律第八十二号）第二条第一項に規定する農薬をいう。）又は種苗</Sentence>
              </Column>
            </ItemSentence>
          </Item>
          <Item Num="2">
            <ItemTitle>二</ItemTitle>
            <ItemSentence>
              <Column Num="1">
                <Sentence Num="1" WritingMode="vertical">前条第一項第六号から第八号までに掲げる農林水産物</Sentence>
              </Column>
              <Column Num="2">
                <Sentence Num="1" WritingMode="vertical">それぞれ当該農林水産物の生産に用いられる飼料（当該飼料に供する飼料作物の種苗を含む。）又は動物用医薬品（医薬品、医療機器等の品質、有効性及び安全性の確保等に関する法律（昭和三十五年法律第百四十五号）第二条第一項に規定する医薬品であって専ら動物のために使用することが目的とされているものをいう。）</Sentence>
              </Column>
            </ItemSentence>
          </Item>
        </Paragraph>
      </Article>
      <Article Num="3">
        <ArticleCaption>（指定行政機関）</ArticleCaption>
        <ArticleTitle>第三条</ArticleTitle>
        <Paragraph Num="1">
          <ParagraphNum/>
          <ParagraphSentence>
            <Sentence Num="1" WritingMode="vertical">法第二条第六号の政令で定める機関は、次に掲げる機関とする。</Sentence>
          </ParagraphSentence>
          <Item Num="1">
            <ItemTitle>一</ItemTitle>
            <ItemSentence>
              <Sentence Num="1" WritingMode="vertical">内閣府</Sentence>
            </ItemSentence>
          </Item>
          <Item Num="2">
            <ItemTitle>二</ItemTitle>
            <ItemSentence>
              <Sentence Num="1" WritingMode="vertical">国家公安委員会</Sentence>
            </ItemSentence>
          </Item>
          <Item Num="3">
            <ItemTitle>三</ItemTitle>
            <ItemSentence>
              <Sentence Num="1" WritingMode="vertical">警察庁</Sentence>
            </ItemSentence>
          </Item>
          <Item Num="4">
            <ItemTitle>四</ItemTitle>
            <ItemSentence>
              <Sentence Num="1" WritingMode="vertical">金融庁</Sentence>
            </ItemSentence>
          </Item>
          <Item Num="5">
            <ItemTitle>五</ItemTitle>
            <ItemSentence>
              <Sentence Num="1" WritingMode="vertical">消費者庁</Sentence>
            </ItemSentence>
          </Item>
          <Item Num="6">
            <ItemTitle>六</ItemTitle>
            <ItemSentence>
              <Sentence Num="1" WritingMode="vertical">こども家庭庁</Sentence>
            </ItemSentence>
          </Item>
          <Item Num="7">
            <ItemTitle>七</ItemTitle>
            <ItemSentence>
              <Sentence Num="1" WritingMode="vertical">デジタル庁</Sentence>
            </ItemSentence>
          </Item>
          <Item Num="8">
            <ItemTitle>八</ItemTitle>
            <ItemSentence>
              <Sentence Num="1" WritingMode="vertical">総務省</Sentence>
            </ItemSentence>
          </Item>
          <Item Num="9">
            <ItemTitle>九</ItemTitle>
            <ItemSentence>
              <Sentence Num="1" WritingMode="vertical">法務省</Sentence>
            </ItemSentence>
          </Item>
          <Item Num="10">
            <ItemTitle>十</ItemTitle>
            <ItemSentence>
              <Sentence Num="1" WritingMode="vertical">外務省</Sentence>
            </ItemSentence>
          </Item>
          <Item Num="11">
            <ItemTitle>十一</ItemTitle>
            <ItemSentence>
              <Sentence Num="1" WritingMode="vertical">財務省</Sentence>
            </ItemSentence>
          </Item>
          <Item Num="12">
            <ItemTitle>十二</ItemTitle>
            <ItemSentence>
              <Sentence Num="1" WritingMode="vertical">国税庁</Sentence>
            </ItemSentence>
          </Item>
          <Item Num="13">
            <ItemTitle>十三</ItemTitle>
            <ItemSentence>
              <Sentence Num="1" WritingMode="vertical">文部科学省</Sentence>
            </ItemSentence>
          </Item>
          <Item Num="14">
            <ItemTitle>十四</ItemTitle>
            <ItemSentence>
              <Sentence Num="1" WritingMode="vertical">厚生労働省</Sentence>
            </ItemSentence>
          </Item>
          <Item Num="15">
            <ItemTitle>十五</ItemTitle>
            <ItemSentence>
              <Sentence Num="1" WritingMode="vertical">検疫所</Sentence>
            </ItemSentence>
          </Item>
          <Item Num="16">
            <ItemTitle>十六</ItemTitle>
            <ItemSentence>
              <Sentence Num="1" WritingMode="vertical">農林水産省</Sentence>
            </ItemSentence>
          </Item>
          <Item Num="17">
            <ItemTitle>十七</ItemTitle>
            <ItemSentence>
              <Sentence Num="1" WritingMode="vertical">植物防疫所</Sentence>
            </ItemSentence>
          </Item>
          <Item Num="18">
            <ItemTitle>十八</ItemTitle>
            <ItemSentence>
              <Sentence Num="1" WritingMode="vertical">那覇植物防疫事務所</Sentence>
            </ItemSentence>
          </Item>
          <Item Num="19">
            <ItemTitle>十九</ItemTitle>
            <ItemSentence>
              <Sentence Num="1" WritingMode="vertical">動物検疫所</Sentence>
            </ItemSentence>
          </Item>
          <Item Num="20">
            <ItemTitle>二十</ItemTitle>
            <ItemSentence>
              <Sentence Num="1" WritingMode="vertical">動物医薬品検査所</Sentence>
            </ItemSentence>
          </Item>
          <Item Num="21">
            <ItemTitle>二十一</ItemTitle>
            <ItemSentence>
              <Sentence Num="1" WritingMode="vertical">経済産業省</Sentence>
            </ItemSentence>
          </Item>
          <Item Num="22">
            <ItemTitle>二十二</ItemTitle>
            <ItemSentence>
              <Sentence Num="1" WritingMode="vertical">資源エネルギー庁</Sentence>
            </ItemSentence>
          </Item>
          <Item Num="23">
            <ItemTitle>二十三</ItemTitle>
            <ItemSentence>
              <Sentence Num="1" WritingMode="vertical">中小企業庁</Sentence>
            </ItemSentence>
          </Item>
          <Item Num="24">
            <ItemTitle>二十四</ItemTitle>
            <ItemSentence>
              <Sentence Num="1" WritingMode="vertical">国土交通省</Sentence>
            </ItemSentence>
          </Item>
          <Item Num="25">
            <ItemTitle>二十五</ItemTitle>
            <ItemSentence>
              <Sentence Num="1" WritingMode="vertical">気象庁</Sentence>
            </ItemSentence>
          </Item>
          <Item Num="26">
            <ItemTitle>二十六</ItemTitle>
            <ItemSentence>
              <Sentence Num="1" WritingMode="vertical">海上保安庁</Sentence>
            </ItemSentence>
          </Item>
          <Item Num="27">
            <ItemTitle>二十七</ItemTitle>
            <ItemSentence>
              <Sentence Num="1" WritingMode="vertical">環境省</Sentence>
            </ItemSentence>
          </Item>
          <Item Num="28">
            <ItemTitle>二十八</ItemTitle>
            <ItemSentence>
              <Sentence Num="1" WritingMode="vertical">防衛省</Sentence>
            </ItemSentence>
          </Item>
          <Item Num="29">
            <ItemTitle>二十九</ItemTitle>
            <ItemSentence>
              <Sentence Num="1" WritingMode="vertical">防衛装備庁</Sentence>
            </ItemSentence>
          </Item>
        </Paragraph>
      </Article>
      <Article Num="4">
        <ArticleCaption>（指定地方行政機関）</ArticleCaption>
        <ArticleTitle>第四条</ArticleTitle>
        <Paragraph Num="1">
          <ParagraphNum/>
          <ParagraphSentence>
            <Sentence Num="1" WritingMode="vertical">法第二条第七号の政令で定める国の地方行政機関は、次に掲げる機関とする。</Sentence>
          </ParagraphSentence>
          <Item Num="1">
            <ItemTitle>一</ItemTitle>
            <ItemSentence>
              <Sentence Num="1" WritingMode="vertical">沖縄総合事務局</Sentence>
            </ItemSentence>
          </Item>
          <Item Num="2">
            <ItemTitle>二</ItemTitle>
            <ItemSentence>
              <Sentence Num="1" WritingMode="vertical">管区警察局</Sentence>
            </ItemSentence>
          </Item>
          <Item Num="3">
            <ItemTitle>三</ItemTitle>
            <ItemSentence>
              <Sentence Num="1" WritingMode="vertical">東京都警察情報通信部</Sentence>
            </ItemSentence>
          </Item>
          <Item Num="4">
            <ItemTitle>四</ItemTitle>
            <ItemSentence>
              <Sentence Num="1" WritingMode="vertical">北海道警察情報通信部</Sentence>
            </ItemSentence>
          </Item>
          <Item Num="5">
            <ItemTitle>五</ItemTitle>
            <ItemSentence>
              <Sentence Num="1" WritingMode="vertical">財務局</Sentence>
            </ItemSentence>
          </Item>
          <Item Num="6">
            <ItemTitle>六</ItemTitle>
            <ItemSentence>
              <Sentence Num="1" WritingMode="vertical">福岡財務支局</Sentence>
            </ItemSentence>
          </Item>
          <Item Num="7">
            <ItemTitle>七</ItemTitle>
            <ItemSentence>
              <Sentence Num="1" WritingMode="vertical">税関</Sentence>
            </ItemSentence>
          </Item>
          <Item Num="8">
            <ItemTitle>八</ItemTitle>
            <ItemSentence>
              <Sentence Num="1" WritingMode="vertical">沖縄地区税関</Sentence>
            </ItemSentence>
          </Item>
          <Item Num="9">
            <ItemTitle>九</ItemTitle>
            <ItemSentence>
              <Sentence Num="1" WritingMode="vertical">国税局</Sentence>
            </ItemSentence>
          </Item>
          <Item Num="10">
            <ItemTitle>十</ItemTitle>
            <ItemSentence>
              <Sentence Num="1" WritingMode="vertical">沖縄国税事務所</Sentence>
            </ItemSentence>
          </Item>
          <Item Num="11">
            <ItemTitle>十一</ItemTitle>
            <ItemSentence>
              <Sentence Num="1" WritingMode="vertical">地方農政局</Sentence>
            </ItemSentence>
          </Item>
          <Item Num="12">
            <ItemTitle>十二</ItemTitle>
            <ItemSentence>
              <Sentence Num="1" WritingMode="vertical">北海道農政事務所</Sentence>
            </ItemSentence>
          </Item>
          <Item Num="13">
            <ItemTitle>十三</ItemTitle>
            <ItemSentence>
              <Sentence Num="1" WritingMode="vertical">経済産業局</Sentence>
            </ItemSentence>
          </Item>
          <Item Num="14">
            <ItemTitle>十四</ItemTitle>
            <ItemSentence>
              <Sentence Num="1" WritingMode="vertical">地方整備局</Sentence>
            </ItemSentence>
          </Item>
          <Item Num="15">
            <ItemTitle>十五</ItemTitle>
            <ItemSentence>
              <Sentence Num="1" WritingMode="vertical">北海道開発局</Sentence>
            </ItemSentence>
          </Item>
          <Item Num="16">
            <ItemTitle>十六</ItemTitle>
            <ItemSentence>
              <Sentence Num="1" WritingMode="vertical">地方運輸局</Sentence>
            </ItemSentence>
          </Item>
          <Item Num="17">
            <ItemTitle>十七</ItemTitle>
            <ItemSentence>
              <Sentence Num="1" WritingMode="vertical">地方航空局</Sentence>
            </ItemSentence>
          </Item>
          <Item Num="18">
            <ItemTitle>十八</ItemTitle>
            <ItemSentence>
              <Sentence Num="1" WritingMode="vertical">航空交通管制部</Sentence>
            </ItemSentence>
          </Item>
          <Item Num="19">
            <ItemTitle>十九</ItemTitle>
            <ItemSentence>
              <Sentence Num="1" WritingMode="vertical">管区気象台</Sentence>
            </ItemSentence>
          </Item>
          <Item Num="20">
            <ItemTitle>二十</ItemTitle>
            <ItemSentence>
              <Sentence Num="1" WritingMode="vertical">沖縄気象台</Sentence>
            </ItemSentence>
          </Item>
          <Item Num="21">
            <ItemTitle>二十一</ItemTitle>
            <ItemSentence>
              <Sentence Num="1" WritingMode="vertical">管区海上保安本部</Sentence>
            </ItemSentence>
          </Item>
          <Item Num="22">
            <ItemTitle>二十二</ItemTitle>
            <ItemSentence>
              <Sentence Num="1" WritingMode="vertical">地方環境事務所</Sentence>
            </ItemSentence>
          </Item>
          <Item Num="23">
            <ItemTitle>二十三</ItemTitle>
            <ItemSentence>
              <Sentence Num="1" WritingMode="vertical">地方防衛局</Sentence>
            </ItemSentence>
          </Item>
        </Paragraph>
      </Article>
    </MainProvision>
    <SupplProvision>
      <SupplProvisionLabel>附　則</SupplProvisionLabel>
      <Paragraph Num="1">
        <ParagraphNum/>
        <ParagraphSentence>
          <Sentence Num="1" WritingMode="vertical">この政令は、法の施行の日（令和七年四月一日）から施行する。</Sentence>
        </ParagraphSentence>
      </Paragraph>
    </SupplProvision>
  </LawBody>
</Law>
