<?xml version="1.0" encoding="UTF-8" standalone="no"?>
<Law Lang="ja" Era="Heisei" Year="22" PromulgateMonth="06" PromulgateDay="24" LawType="MinisterialOrdinance" Num="38">
  <LawNum>平成二十二年経済産業省令第三十八号</LawNum>
  <LawBody>
    <LawTitle Kana="くらすたーだんとうのせいぞうのきんしおよびしょじのきせいとうにかんするほうりつせこうきそく" Abbrev="クラスター弾等禁止法施行規則" AbbrevKana="ク">クラスター弾等の製造の禁止及び所持の規制等に関する法律施行規則</LawTitle>
    <EnactStatement>クラスター弾等の製造の禁止及び所持の規制等に関する法律（平成二十一年法律第八十五号）第五条第二項、第八条第一項、第十一条第二項、第十四条並びに第十五条第一項及び第二項の規定に基づき、並びに同法を実施するため、クラスター弾等の製造の禁止及び所持の規制等に関する法律施行規則を次のように定める。</EnactStatement>
    <MainProvision>
      <Article Delete="false" Hide="false" Num="1">
        <ArticleCaption>（所持の許可の申請）</ArticleCaption>
        <ArticleTitle>第一条</ArticleTitle>
        <Paragraph Hide="false" Num="1" OldStyle="false">
          <ParagraphNum/>
          <ParagraphSentence>
            <Sentence WritingMode="vertical">クラスター弾等の製造の禁止及び所持の規制等に関する法律（以下「法」という。）第五条第二項の規定により同条第一項の許可の申請をしようとする者は、様式第一による所持許可申請書に次の書類を添えて、経済産業大臣に提出しなければならない。</Sentence>
          </ParagraphSentence>
          <Item Delete="false" Hide="false" Num="1">
            <ItemTitle>一</ItemTitle>
            <ItemSentence>
              <Sentence WritingMode="vertical">申請者（申請者が法人である場合にあっては、その法人及びその法人の業務を行う役員）が法第六条各号に該当しないことを説明した書面</Sentence>
            </ItemSentence>
          </Item>
          <Item Delete="false" Hide="false" Num="2">
            <ItemTitle>二</ItemTitle>
            <ItemSentence>
              <Sentence WritingMode="vertical">申請者が法人である場合にあっては、その法人の定款及び登記事項証明書</Sentence>
            </ItemSentence>
          </Item>
        </Paragraph>
      </Article>
      <Article Num="1_2">
        <ArticleCaption>（法第六条第四号の経済産業省令で定める者）</ArticleCaption>
        <ArticleTitle>第一条の二</ArticleTitle>
        <Paragraph Num="1">
          <ParagraphNum/>
          <ParagraphSentence>
            <Sentence>法第六条第四号の経済産業省令で定める者は、精神の機能の障害によりクラスター弾等の所持を適正に行うに当たって必要な認知、判断及び意思疎通を適切に行うことができない者とする。</Sentence>
          </ParagraphSentence>
        </Paragraph>
      </Article>
      <Article Delete="false" Hide="false" Num="2">
        <ArticleCaption>（変更の許可の申請）</ArticleCaption>
        <ArticleTitle>第二条</ArticleTitle>
        <Paragraph Hide="false" Num="1" OldStyle="false">
          <ParagraphNum/>
          <ParagraphSentence>
            <Sentence WritingMode="vertical">法第八条第一項の規定により変更の許可を受けようとする者は、様式第二による変更許可申請書を経済産業大臣に提出しなければならない。</Sentence>
          </ParagraphSentence>
        </Paragraph>
      </Article>
      <Article Delete="false" Hide="false" Num="3">
        <ArticleCaption>（変更の届出）</ArticleCaption>
        <ArticleTitle>第三条</ArticleTitle>
        <Paragraph Hide="false" Num="1" OldStyle="false">
          <ParagraphNum/>
          <ParagraphSentence>
            <Sentence WritingMode="vertical">法第八条第二項の規定により届出をしようとする者は、様式第三による変更届出書を経済産業大臣に提出しなければならない。</Sentence>
          </ParagraphSentence>
        </Paragraph>
      </Article>
      <Article Delete="false" Hide="false" Num="4">
        <ArticleCaption>（廃棄等の届出）</ArticleCaption>
        <ArticleTitle>第四条</ArticleTitle>
        <Paragraph Hide="false" Num="1" OldStyle="false">
          <ParagraphNum/>
          <ParagraphSentence>
            <Sentence WritingMode="vertical">法第十一条第二項の規定により届出をしようとする者は、様式第四による廃棄等届出書を経済産業大臣に提出しなければならない。</Sentence>
          </ParagraphSentence>
        </Paragraph>
      </Article>
      <Article Delete="false" Hide="false" Num="5">
        <ArticleCaption>（承継の届出）</ArticleCaption>
        <ArticleTitle>第五条</ArticleTitle>
        <Paragraph Hide="false" Num="1" OldStyle="false">
          <ParagraphNum/>
          <ParagraphSentence>
            <Sentence WritingMode="vertical">法第十三条第二項の規定により届出をしようとする者は、様式第五による許可所持者地位承継届出書に次の書類を添えて、経済産業大臣に提出しなければならない。</Sentence>
          </ParagraphSentence>
          <Item Delete="false" Hide="false" Num="1">
            <ItemTitle>一</ItemTitle>
            <ItemSentence>
              <Sentence WritingMode="vertical">法第十三条第一項の規定により許可所持者の地位を承継した相続人であって、二人以上の相続人の全員の同意により選定されたものにあっては、様式第六による許可所持者相続同意証明書及び戸籍の謄本又は全部事項証明書</Sentence>
            </ItemSentence>
          </Item>
          <Item Delete="false" Hide="false" Num="2">
            <ItemTitle>二</ItemTitle>
            <ItemSentence>
              <Sentence WritingMode="vertical">法第十三条第一項の規定により許可所持者の地位を承継した相続人であって、前号の相続人以外のものにあっては、様式第七による許可所持者相続証明書及び戸籍の謄本又は全部事項証明書</Sentence>
            </ItemSentence>
          </Item>
          <Item Delete="false" Hide="false" Num="3">
            <ItemTitle>三</ItemTitle>
            <ItemSentence>
              <Sentence WritingMode="vertical">法第十三条第一項の規定により合併によって許可所持者の地位を承継した法人にあっては、その法人の定款及び登記事項証明書</Sentence>
            </ItemSentence>
          </Item>
        </Paragraph>
      </Article>
      <Article Delete="false" Hide="false" Num="6">
        <ArticleCaption>（所持の届出）</ArticleCaption>
        <ArticleTitle>第六条</ArticleTitle>
        <Paragraph Hide="false" Num="1" OldStyle="false">
          <ParagraphNum/>
          <ParagraphSentence>
            <Sentence WritingMode="vertical">法第十四条の規定により届出をしようとする者は、様式第八による届出書を経済産業大臣に提出しなければならない。</Sentence>
          </ParagraphSentence>
        </Paragraph>
      </Article>
      <Article Delete="false" Hide="false" Num="7">
        <ArticleCaption>（帳簿の記載事項）</ArticleCaption>
        <ArticleTitle>第七条</ArticleTitle>
        <Paragraph Hide="false" Num="1" OldStyle="false">
          <ParagraphNum/>
          <ParagraphSentence>
            <Sentence WritingMode="vertical">法第十五条第一項の経済産業省令で定める事項は、次に掲げるものとする。</Sentence>
          </ParagraphSentence>
          <Item Delete="false" Hide="false" Num="1">
            <ItemTitle>一</ItemTitle>
            <ItemSentence>
              <Sentence WritingMode="vertical">クラスター弾等（法第二条第一項のクラスター弾等をいう。以下同じ。）の型式及び数量</Sentence>
            </ItemSentence>
          </Item>
          <Item Delete="false" Hide="false" Num="2">
            <ItemTitle>二</ItemTitle>
            <ItemSentence>
              <Sentence WritingMode="vertical">クラスター弾等の数量が増減した場合の理由及び年月日並びに増減したクラスター弾等の型式及び数量</Sentence>
            </ItemSentence>
          </Item>
        </Paragraph>
        <Paragraph Hide="false" Num="2" OldStyle="false">
          <ParagraphNum>２</ParagraphNum>
          <ParagraphSentence>
            <Sentence WritingMode="vertical">法第十五条第二項の規定による前項に規定する事項を記載した帳簿の保存期間は、許可に係るクラスター弾等を所持することとなった日から当該許可に係るクラスター弾等の全部を所持しないこととなった日から起算して五年を経過する日までの間とする。</Sentence>
          </ParagraphSentence>
        </Paragraph>
      </Article>
      <Article Delete="false" Hide="false" Num="8">
        <ArticleCaption>（報告）</ArticleCaption>
        <ArticleTitle>第八条</ArticleTitle>
        <Paragraph Hide="false" Num="1" OldStyle="false">
          <ParagraphNum/>
          <ParagraphSentence>
            <Sentence WritingMode="vertical">法第五条の規定による許可所持者は、前条の記載事項を毎年一月一日から十二月三十一日までの期間について集計し、法第十六条第一項の規定に基づき、当該期間の経過後五十日以内に経済産業大臣に報告しなければならない。</Sentence>
          </ParagraphSentence>
        </Paragraph>
      </Article>
      <Article Delete="false" Hide="false" Num="9">
        <ArticleCaption>（立入検査の証明書）</ArticleCaption>
        <ArticleTitle>第九条</ArticleTitle>
        <Paragraph Hide="false" Num="1" OldStyle="false">
          <ParagraphNum/>
          <ParagraphSentence>
            <Sentence WritingMode="vertical">経済産業大臣がその職員に携帯させる法第十七条第二項の証明書は、様式第九によるものとする。</Sentence>
          </ParagraphSentence>
        </Paragraph>
      </Article>
    </MainProvision>
    <SupplProvision Extract="true">
      <SupplProvisionLabel>附　則</SupplProvisionLabel>
      <Article Delete="false" Hide="false" Num="1">
        <ArticleCaption>（施行期日）</ArticleCaption>
        <ArticleTitle>第一条</ArticleTitle>
        <Paragraph Hide="false" Num="1" OldStyle="false">
          <ParagraphNum/>
          <ParagraphSentence>
            <Sentence WritingMode="vertical">この省令は、法の施行の日から施行する。</Sentence>
          </ParagraphSentence>
        </Paragraph>
      </Article>
    </SupplProvision>
    <SupplProvision AmendLawNum="令和元年七月一日経済産業省令第一七号">
      <SupplProvisionLabel>附　則</SupplProvisionLabel>
      <Paragraph Hide="false" Num="1" OldStyle="false">
        <ParagraphNum/>
        <ParagraphSentence>
          <Sentence WritingMode="vertical">この省令は、不正競争防止法等の一部を改正する法律の施行の日（令和元年七月一日）から施行する。</Sentence>
        </ParagraphSentence>
      </Paragraph>
    </SupplProvision>
    <SupplProvision AmendLawNum="令和元年九月一一日経済産業省令第三六号">
      <SupplProvisionLabel>附　則</SupplProvisionLabel>
      <Paragraph Num="1">
        <ParagraphNum/>
        <ParagraphSentence>
          <Sentence>この省令は、成年被後見人等の権利の制限に係る措置の適正化等を図るための関係法律の整備に関する法律の施行の日（令和元年九月十四日）から施行する。</Sentence>
        </ParagraphSentence>
      </Paragraph>
    </SupplProvision>
    <SupplProvision AmendLawNum="令和二年一二月二八日経済産業省令第九二号">
      <SupplProvisionLabel>附　則</SupplProvisionLabel>
      <Article Num="1">
        <ArticleCaption>（施行期日）</ArticleCaption>
        <ArticleTitle>第一条</ArticleTitle>
        <Paragraph Num="1">
          <ParagraphNum/>
          <ParagraphSentence>
            <Sentence>この省令は、公布の日から施行する。</Sentence>
          </ParagraphSentence>
        </Paragraph>
      </Article>
      <Article Num="2">
        <ArticleCaption>（経過措置）</ArticleCaption>
        <ArticleTitle>第二条</ArticleTitle>
        <Paragraph Num="1">
          <ParagraphNum/>
          <ParagraphSentence>
            <Sentence>この省令の施行の際現にあるこの省令による改正前の様式（次項において「旧様式」という。）により使用されている書類（第九十二条による改正前の電気事業法等の一部を改正する等の法律の施行に伴う経過措置に関する省令様式第十三を除く。）は、この省令による改正後の様式によるものとみなす。</Sentence>
          </ParagraphSentence>
        </Paragraph>
        <Paragraph Num="2">
          <ParagraphNum>２</ParagraphNum>
          <ParagraphSentence>
            <Sentence>この省令の施行の際現にある旧様式による用紙（第九十二条による改正前の電気事業法等の一部を改正する等の法律の施行に伴う経過措置に関する省令様式第十三を除く。）については、当分の間、これを取り繕って使用することができる。</Sentence>
          </ParagraphSentence>
        </Paragraph>
      </Article>
    </SupplProvision>
    <AppdxStyle>
      <AppdxStyleTitle WritingMode="vertical">様式第１</AppdxStyleTitle>
      <RelatedArticleNum>（第１条関係）</RelatedArticleNum>
      <StyleStruct>
        <Style>
          <Fig src=""/>
        </Style>
      </StyleStruct>
    </AppdxStyle>
    <AppdxStyle>
      <AppdxStyleTitle WritingMode="vertical">様式第２</AppdxStyleTitle>
      <RelatedArticleNum>（第２条関係）</RelatedArticleNum>
      <StyleStruct>
        <Style>
          <Fig src=""/>
        </Style>
      </StyleStruct>
    </AppdxStyle>
    <AppdxStyle>
      <AppdxStyleTitle WritingMode="vertical">様式第３</AppdxStyleTitle>
      <RelatedArticleNum>（第３条関係）</RelatedArticleNum>
      <StyleStruct>
        <Style>
          <Fig src=""/>
        </Style>
      </StyleStruct>
    </AppdxStyle>
    <AppdxStyle>
      <AppdxStyleTitle WritingMode="vertical">様式第４</AppdxStyleTitle>
      <RelatedArticleNum>（第４条関係）</RelatedArticleNum>
      <StyleStruct>
        <Style>
          <Fig src=""/>
        </Style>
      </StyleStruct>
    </AppdxStyle>
    <AppdxStyle>
      <AppdxStyleTitle WritingMode="vertical">様式第５</AppdxStyleTitle>
      <RelatedArticleNum>（第５条関係）</RelatedArticleNum>
      <StyleStruct>
        <Style>
          <Fig src=""/>
        </Style>
      </StyleStruct>
    </AppdxStyle>
    <AppdxStyle>
      <AppdxStyleTitle WritingMode="vertical">様式第６</AppdxStyleTitle>
      <RelatedArticleNum>（第５条関係）</RelatedArticleNum>
      <StyleStruct>
        <Style>
          <Fig src=""/>
        </Style>
      </StyleStruct>
    </AppdxStyle>
    <AppdxStyle>
      <AppdxStyleTitle WritingMode="vertical">様式第７</AppdxStyleTitle>
      <RelatedArticleNum>（第５条関係）</RelatedArticleNum>
      <StyleStruct>
        <Style>
          <Fig src=""/>
        </Style>
      </StyleStruct>
    </AppdxStyle>
    <AppdxStyle>
      <AppdxStyleTitle WritingMode="vertical">様式第８</AppdxStyleTitle>
      <RelatedArticleNum>（第６条関係）</RelatedArticleNum>
      <StyleStruct>
        <Style>
          <Fig src=""/>
        </Style>
      </StyleStruct>
    </AppdxStyle>
    <AppdxStyle>
      <AppdxStyleTitle WritingMode="vertical">様式第９</AppdxStyleTitle>
      <RelatedArticleNum>（第９条関係）</RelatedArticleNum>
      <StyleStruct>
        <Style>
          <Fig src="./pict/pict_2005291705_009.pdf"/>
        </Style>
      </StyleStruct>
    </AppdxStyle>
  </LawBody>
</Law>
