<?xml version="1.0" encoding="UTF-8" standalone="no"?>
<Law AmendmentId="431M60000048001" AmendmentNum="平成三十一年総務省・財務省令第一号" Era="Heisei" Lang="ja" LawType="MinisterialOrdinance" Num="001" Year="30" PromulgateMonth="03" PromulgateDay="30">
  <LawNum>平成三十年総務省・財務省令第一号</LawNum>
  <LawBody>
    <LawTitle Kana="へいせいさんじゅうねんどにけるちほうこうきょうだんたいきんゆうきこうほうふそくだいじゅうよんじょうのきていによりくににきぞくさせるものとするきんがくをさだめるしょうれい" Abbrev="" AbbrevKana="">平成三十年度における地方公共団体金融機構法附則第十四条の規定により国に帰属させるものとする金額を定める省令</LawTitle>
    <EnactStatement>地方公共団体金融機構法（平成十九年法律第六十四号）附則第十四条の規定に基づき、平成三十年度における地方公共団体金融機構法附則第十四条の規定により国に帰属させるものとする金額を定める省令を次のように定める。</EnactStatement>
    <MainProvision>
      <Paragraph Hide="false" Num="1" OldStyle="false">
        <ParagraphNum/>
        <ParagraphSentence>
          <Sentence WritingMode="vertical">地方公共団体金融機構法附則第十四条の規定により国に帰属させるものとする金額は、公庫債権金利変動準備金四千億六千四百二十三万九千八百二十四円とする。</Sentence>
        </ParagraphSentence>
      </Paragraph>
    </MainProvision>
    <SupplProvision>
      <SupplProvisionLabel>附　則</SupplProvisionLabel>
      <Paragraph Hide="false" Num="1" OldStyle="false">
        <ParagraphNum/>
        <ParagraphSentence>
          <Sentence WritingMode="vertical">この省令は、平成三十年四月一日から施行する。</Sentence>
        </ParagraphSentence>
      </Paragraph>
    </SupplProvision>
    <SupplProvision AmendLawNum="平成三一年三月二五日総務省・財務省令第一号" Type="Amend">
      <SupplProvisionLabel>附　則</SupplProvisionLabel>
      <Paragraph Hide="false" Num="1" OldStyle="false">
        <ParagraphNum/>
        <ParagraphSentence>
          <Sentence WritingMode="vertical">この省令は、平成三十一年三月二十五日から施行する。</Sentence>
        </ParagraphSentence>
      </Paragraph>
    </SupplProvision>
  </LawBody>
</Law>
