<?xml version="1.0" encoding="UTF-8" standalone="no"?>
<Law Era="Heisei" Lang="ja" LawType="MinisterialOrdinance" Num="3" Year="13">
  <LawNum>平成十三年国土交通省・環境省令第三号</LawNum>
  <LawBody>
    <LawTitle>特定工場における公害防止組織の整備に関する法律施行令別表第三の三の項の下欄及び七の項の下欄に規定する講習に関する省令</LawTitle>
    <EnactStatement>特定工場における公害防止組織の整備に関する法律施行令（昭和四十六年政令第二百六十四号）を実施するため、特定工場における公害防止組織の整備に関する法律施行令別表第三の三の項の下欄及び七の項の下欄に規定する講習に関する省令を次のように定める。</EnactStatement>
    <MainProvision>
      <Article Num="1">
        <ArticleCaption>（指定の基準）</ArticleCaption>
        <ArticleTitle>第一条</ArticleTitle>
        <Paragraph Num="1">
          <ParagraphNum/>
          <ParagraphSentence>
            <Sentence>特定工場における公害防止組織の整備に関する法律施行令（以下「令」という。）別表第三の三の項の下欄及び七の項の下欄の規定による指定は、次に掲げる基準に適合すると認められる者が実施する講習について行う。</Sentence>
          </ParagraphSentence>
          <Item Num="1">
            <ItemTitle>一</ItemTitle>
            <ItemSentence>
              <Sentence>職員、講習事務の実施の方法その他の事項についての講習事務の実施に関する計画が講習事務の適正かつ確実な実施のために適切なものであること。</Sentence>
            </ItemSentence>
          </Item>
          <Item Num="2">
            <ItemTitle>二</ItemTitle>
            <ItemSentence>
              <Sentence>前号の講習事務の実施に関する計画を適正かつ確実に実施するに足りる経理的基礎及び技術的能力があること。</Sentence>
            </ItemSentence>
          </Item>
        </Paragraph>
      </Article>
      <Article Num="2">
        <ArticleCaption>（指定）</ArticleCaption>
        <ArticleTitle>第二条</ArticleTitle>
        <Paragraph Num="1">
          <ParagraphNum/>
          <ParagraphSentence>
            <Sentence>令別表第三の三の項の下欄及び七の項の下欄の規定により指定する講習を実施する者の名称及び主たる事務所の所在地並びに講習の名称は、次のとおりとする。</Sentence>
          </ParagraphSentence>
          <TableStruct>
            <Table>
              <TableRow>
                <TableColumn rowspan="2">
                  <Sentence>講習</Sentence>
                </TableColumn>
                <TableColumn colspan="2">
                  <Sentence>講習を実施する者</Sentence>
                </TableColumn>
                <TableColumn rowspan="2">
                  <Sentence>講習の名称</Sentence>
                </TableColumn>
              </TableRow>
              <TableRow>
                <TableColumn>
                  <Sentence>名称</Sentence>
                </TableColumn>
                <TableColumn>
                  <Sentence>主たる事務所の所在地</Sentence>
                </TableColumn>
              </TableRow>
              <TableRow>
                <TableColumn>
                  <Sentence>令別表第三の三の項の下欄の規定により指定する講習</Sentence>
                </TableColumn>
                <TableColumn>
                  <Sentence>社団法人日本舶用工業会</Sentence>
                </TableColumn>
                <TableColumn>
                  <Sentence>東京都港区虎ノ門一丁目五番十六号</Sentence>
                </TableColumn>
                <TableColumn>
                  <Sentence>大気関係第三種公害防止管理者資格認定講習</Sentence>
                </TableColumn>
              </TableRow>
              <TableRow>
                <TableColumn>
                  <Sentence>令別表第三の七の項の下欄の規定により指定する講習</Sentence>
                </TableColumn>
                <TableColumn>
                  <Sentence>社団法人日本舶用工業会</Sentence>
                </TableColumn>
                <TableColumn>
                  <Sentence>東京都港区虎ノ門一丁目五番十六号</Sentence>
                </TableColumn>
                <TableColumn>
                  <Sentence>水質関係第三種公害防止管理者資格認定講習</Sentence>
                </TableColumn>
              </TableRow>
            </Table>
          </TableStruct>
        </Paragraph>
      </Article>
    </MainProvision>
    <SupplProvision>
      <SupplProvisionLabel>附　則</SupplProvisionLabel>
      <Paragraph Num="1">
        <ParagraphNum>１</ParagraphNum>
        <ParagraphSentence>
          <Sentence>この省令は、公布の日から施行する。</Sentence>
        </ParagraphSentence>
      </Paragraph>
      <Paragraph Num="2">
        <ParagraphNum>２</ParagraphNum>
        <ParagraphSentence>
          <Sentence>第二条の規定は、平成十六年十月三十一日限り、その効力を失う。</Sentence>
        </ParagraphSentence>
      </Paragraph>
      <Paragraph Num="3">
        <ParagraphNum>３</ParagraphNum>
        <ParagraphSentence>
          <Sentence>前項に規定する日以前に第二条に規定する講習の課程を修了した者は、同日後においても、なお令別表第三の三の項の下欄及び七の項の下欄に規定する講習の課程を修了したものとみなす。</Sentence>
        </ParagraphSentence>
      </Paragraph>
    </SupplProvision>
    <SupplProvision AmendLawId="414003" AmendLawNum="平成一四年六月七日国土交通省・環境省令第三号" Id="a8c5a140-1925-11e8-a136-005056b30d52">
      <SupplProvisionLabel>附　則</SupplProvisionLabel>
      <Paragraph Num="1">
        <ParagraphNum/>
        <ParagraphSentence>
          <Sentence>この省令は、公布の日から施行する。</Sentence>
        </ParagraphSentence>
      </Paragraph>
    </SupplProvision>
    <SupplProvision AmendLawId="415003" AmendLawNum="平成一五年六月三日国土交通省・環境省令第三号" Id="a8f4dd66-1925-11e8-a136-005056b30d52">
      <SupplProvisionLabel>附　則</SupplProvisionLabel>
      <Paragraph Num="1">
        <ParagraphNum/>
        <ParagraphSentence>
          <Sentence>この省令は、公布の日から施行する。</Sentence>
        </ParagraphSentence>
      </Paragraph>
    </SupplProvision>
    <SupplProvision AmendLawId="416003" AmendLawNum="平成一六年六月二三日国土交通省・環境省令第三号" Id="a9241810-1925-11e8-a136-005056b30d52">
      <SupplProvisionLabel>附　則</SupplProvisionLabel>
      <Paragraph Num="1">
        <ParagraphNum/>
        <ParagraphSentence>
          <Sentence>この省令は、公布の日から施行する。</Sentence>
        </ParagraphSentence>
      </Paragraph>
    </SupplProvision>
  </LawBody>
</Law>
