<?xml version="1.0" encoding="UTF-8"?>
<Law Era="Reiwa" Year="05" Num="334" LawType="CabinetOrder" Lang="ja" PromulgateMonth="11" PromulgateDay="24">
  <LawNum>令和五年政令第三百三十四号</LawNum>
  <LawBody>
    <LawTitle Kana="かいじょううんそうほうとうのいちぶをかいせいするほうりつのしこうにともなうかんけいせいれいのせいびおよびけいかそちにかんするせいれい" Abbrev="" AbbrevKana="">海上運送法等の一部を改正する法律の施行に伴う関係政令の整備及び経過措置に関する政令</LawTitle>
    <EnactStatement>内閣は、海上運送法等の一部を改正する法律（令和五年法律第二十四号）の施行に伴い、並びに海上運送法（昭和二十四年法律第百八十七号）第四十五条の四第一項、船舶職員及び小型船舶操縦者法（昭和二十六年法律第百四十九号）第十八条第一項、第二十三条の二十七第一項、第二十三条の二十八、第二十三条の三十二、第二十三条の三十四、第二十三条の三十五第一項及び第二十三条の三十九第一項並びに海上運送法等の一部を改正する法律附則第十条の規定に基づき、この政令を制定する。</EnactStatement>
    <TOC>
      <TOCLabel>目次</TOCLabel>
      <TOCChapter Num="1">
        <ChapterTitle>第一章　関係政令の整備</ChapterTitle>
        <ArticleRange>（第一条―第四条）</ArticleRange>
      </TOCChapter>
      <TOCChapter Num="2">
        <ChapterTitle>第二章　経過措置</ChapterTitle>
        <ArticleRange>（第五条）</ArticleRange>
      </TOCChapter>
      <TOCSupplProvision>
        <SupplProvisionLabel>附則</SupplProvisionLabel>
      </TOCSupplProvision>
    </TOC>
    <MainProvision Extract="true">
      <Chapter Num="2">
        <ChapterTitle>第二章　経過措置</ChapterTitle>
        <Article Num="5">
          <ArticleTitle>第五条</ArticleTitle>
          <Paragraph Num="1">
            <ParagraphNum/>
            <ParagraphSentence>
              <Sentence Num="1" WritingMode="vertical">海上運送法等の一部を改正する法律附則第三条第五項に規定する国土交通大臣の権限は、小型船舶旅客不定期航路事業に係る航路の起点の所在地を管轄する地方運輸局長（運輸監理部長を含む。）が行うものとする。</Sentence>
            </ParagraphSentence>
          </Paragraph>
        </Article>
      </Chapter>
    </MainProvision>
    <SupplProvision>
      <SupplProvisionLabel>附　則</SupplProvisionLabel>
      <Paragraph Num="1">
        <ParagraphNum/>
        <ParagraphSentence>
          <Sentence Num="1" WritingMode="vertical">この政令は、海上運送法等の一部を改正する法律の施行の日（令和六年四月一日）から施行する。</Sentence>
        </ParagraphSentence>
      </Paragraph>
    </SupplProvision>
  </LawBody>
</Law>
