<?xml version="1.0" encoding="UTF-8" standalone="no"?>
<Law Era="Showa" Lang="ja" LawType="CabinetOrder" Num="043" Year="40" PromulgateMonth="03" PromulgateDay="24">
  <LawNum>昭和四十年政令第四十三号</LawNum>
  <LawBody>
    <LawTitle Kana="かせんほうだいよんじょうだいいっこうのすいけいをしていするせいれい" Abbrev="" AbbrevKana="">河川法第四条第一項の水系を指定する政令</LawTitle>
    <EnactStatement>内閣は、河川法（昭和三十九年法律第百六十七号）第四条第一項の規定に基づき、この政令を制定する。</EnactStatement>
    <MainProvision>
      <Paragraph Num="1">
        <ParagraphNum/>
        <ParagraphSentence>
          <Sentence>河川法第四条第一項の水系は、次の各号に掲げるものとする。</Sentence>
        </ParagraphSentence>
        <Item Num="1">
          <ItemTitle>一</ItemTitle>
          <ItemSentence>
            <Sentence>天塩川水系</Sentence>
          </ItemSentence>
        </Item>
        <Item Num="2">
          <ItemTitle>二</ItemTitle>
          <ItemSentence>
            <Sentence>渚滑川水系</Sentence>
          </ItemSentence>
        </Item>
        <Item Num="3">
          <ItemTitle>三</ItemTitle>
          <ItemSentence>
            <Sentence>湧別川水系</Sentence>
          </ItemSentence>
        </Item>
        <Item Num="4">
          <ItemTitle>四</ItemTitle>
          <ItemSentence>
            <Sentence>常呂川水系</Sentence>
          </ItemSentence>
        </Item>
        <Item Num="5">
          <ItemTitle>五</ItemTitle>
          <ItemSentence>
            <Sentence>網走川水系</Sentence>
          </ItemSentence>
        </Item>
        <Item Num="6">
          <ItemTitle>六</ItemTitle>
          <ItemSentence>
            <Sentence>留萌川水系</Sentence>
          </ItemSentence>
        </Item>
        <Item Num="7">
          <ItemTitle>七</ItemTitle>
          <ItemSentence>
            <Sentence>石狩川水系</Sentence>
          </ItemSentence>
        </Item>
        <Item Num="8">
          <ItemTitle>八</ItemTitle>
          <ItemSentence>
            <Sentence>尻別川水系</Sentence>
          </ItemSentence>
        </Item>
        <Item Num="9">
          <ItemTitle>九</ItemTitle>
          <ItemSentence>
            <Sentence>後志利別川水系</Sentence>
          </ItemSentence>
        </Item>
        <Item Num="10">
          <ItemTitle>十</ItemTitle>
          <ItemSentence>
            <Sentence>鵡川水系</Sentence>
          </ItemSentence>
        </Item>
        <Item Num="11">
          <ItemTitle>十一</ItemTitle>
          <ItemSentence>
            <Sentence>沙流川水系</Sentence>
          </ItemSentence>
        </Item>
        <Item Num="12">
          <ItemTitle>十二</ItemTitle>
          <ItemSentence>
            <Sentence>釧路川水系</Sentence>
          </ItemSentence>
        </Item>
        <Item Num="13">
          <ItemTitle>十三</ItemTitle>
          <ItemSentence>
            <Sentence>十勝川水系</Sentence>
          </ItemSentence>
        </Item>
        <Item Num="14">
          <ItemTitle>十四</ItemTitle>
          <ItemSentence>
            <Sentence>岩木川水系</Sentence>
          </ItemSentence>
        </Item>
        <Item Num="15">
          <ItemTitle>十五</ItemTitle>
          <ItemSentence>
            <Sentence>高瀬川水系</Sentence>
          </ItemSentence>
        </Item>
        <Item Num="16">
          <ItemTitle>十六</ItemTitle>
          <ItemSentence>
            <Sentence>馬淵川水系</Sentence>
          </ItemSentence>
        </Item>
        <Item Num="17">
          <ItemTitle>十七</ItemTitle>
          <ItemSentence>
            <Sentence>北上川水系</Sentence>
          </ItemSentence>
        </Item>
        <Item Num="18">
          <ItemTitle>十八</ItemTitle>
          <ItemSentence>
            <Sentence>鳴瀬川水系</Sentence>
          </ItemSentence>
        </Item>
        <Item Num="19">
          <ItemTitle>十九</ItemTitle>
          <ItemSentence>
            <Sentence>名取川水系</Sentence>
          </ItemSentence>
        </Item>
        <Item Num="20">
          <ItemTitle>二十</ItemTitle>
          <ItemSentence>
            <Sentence>阿武隈川水系</Sentence>
          </ItemSentence>
        </Item>
        <Item Num="21">
          <ItemTitle>二十一</ItemTitle>
          <ItemSentence>
            <Sentence>米代川水系</Sentence>
          </ItemSentence>
        </Item>
        <Item Num="22">
          <ItemTitle>二十二</ItemTitle>
          <ItemSentence>
            <Sentence>雄物川水系</Sentence>
          </ItemSentence>
        </Item>
        <Item Num="23">
          <ItemTitle>二十三</ItemTitle>
          <ItemSentence>
            <Sentence>子吉川水系</Sentence>
          </ItemSentence>
        </Item>
        <Item Num="24">
          <ItemTitle>二十四</ItemTitle>
          <ItemSentence>
            <Sentence>最上川水系</Sentence>
          </ItemSentence>
        </Item>
        <Item Num="25">
          <ItemTitle>二十五</ItemTitle>
          <ItemSentence>
            <Sentence>赤川水系</Sentence>
          </ItemSentence>
        </Item>
        <Item Num="26">
          <ItemTitle>二十六</ItemTitle>
          <ItemSentence>
            <Sentence>久慈川水系</Sentence>
          </ItemSentence>
        </Item>
        <Item Num="27">
          <ItemTitle>二十七</ItemTitle>
          <ItemSentence>
            <Sentence>那珂川水系</Sentence>
          </ItemSentence>
        </Item>
        <Item Num="28">
          <ItemTitle>二十八</ItemTitle>
          <ItemSentence>
            <Sentence>利根川水系</Sentence>
          </ItemSentence>
        </Item>
        <Item Num="29">
          <ItemTitle>二十九</ItemTitle>
          <ItemSentence>
            <Sentence>荒川水系（東京都・埼玉県）</Sentence>
          </ItemSentence>
        </Item>
        <Item Num="30">
          <ItemTitle>三十</ItemTitle>
          <ItemSentence>
            <Sentence>多摩川水系</Sentence>
          </ItemSentence>
        </Item>
        <Item Num="31">
          <ItemTitle>三十一</ItemTitle>
          <ItemSentence>
            <Sentence>鶴見川水系</Sentence>
          </ItemSentence>
        </Item>
        <Item Num="32">
          <ItemTitle>三十二</ItemTitle>
          <ItemSentence>
            <Sentence>相模川水系</Sentence>
          </ItemSentence>
        </Item>
        <Item Num="33">
          <ItemTitle>三十三</ItemTitle>
          <ItemSentence>
            <Sentence>荒川水系（新潟県・山形県）</Sentence>
          </ItemSentence>
        </Item>
        <Item Num="34">
          <ItemTitle>三十四</ItemTitle>
          <ItemSentence>
            <Sentence>阿賀野川水系</Sentence>
          </ItemSentence>
        </Item>
        <Item Num="35">
          <ItemTitle>三十五</ItemTitle>
          <ItemSentence>
            <Sentence>信濃川水系</Sentence>
          </ItemSentence>
        </Item>
        <Item Num="36">
          <ItemTitle>三十六</ItemTitle>
          <ItemSentence>
            <Sentence>関川水系</Sentence>
          </ItemSentence>
        </Item>
        <Item Num="37">
          <ItemTitle>三十七</ItemTitle>
          <ItemSentence>
            <Sentence>姫川水系</Sentence>
          </ItemSentence>
        </Item>
        <Item Num="38">
          <ItemTitle>三十八</ItemTitle>
          <ItemSentence>
            <Sentence>黒部川水系</Sentence>
          </ItemSentence>
        </Item>
        <Item Num="39">
          <ItemTitle>三十九</ItemTitle>
          <ItemSentence>
            <Sentence>常願寺川水系</Sentence>
          </ItemSentence>
        </Item>
        <Item Num="40">
          <ItemTitle>四十</ItemTitle>
          <ItemSentence>
            <Sentence>神通川水系</Sentence>
          </ItemSentence>
        </Item>
        <Item Num="41">
          <ItemTitle>四十一</ItemTitle>
          <ItemSentence>
            <Sentence>庄川水系</Sentence>
          </ItemSentence>
        </Item>
        <Item Num="42">
          <ItemTitle>四十二</ItemTitle>
          <ItemSentence>
            <Sentence>小矢部川水系</Sentence>
          </ItemSentence>
        </Item>
        <Item Num="43">
          <ItemTitle>四十三</ItemTitle>
          <ItemSentence>
            <Sentence>手取川水系</Sentence>
          </ItemSentence>
        </Item>
        <Item Num="44">
          <ItemTitle>四十四</ItemTitle>
          <ItemSentence>
            <Sentence>梯川水系</Sentence>
          </ItemSentence>
        </Item>
        <Item Num="45">
          <ItemTitle>四十五</ItemTitle>
          <ItemSentence>
            <Sentence>狩野川水系</Sentence>
          </ItemSentence>
        </Item>
        <Item Num="46">
          <ItemTitle>四十六</ItemTitle>
          <ItemSentence>
            <Sentence>富士川水系</Sentence>
          </ItemSentence>
        </Item>
        <Item Num="47">
          <ItemTitle>四十七</ItemTitle>
          <ItemSentence>
            <Sentence>安倍川水系</Sentence>
          </ItemSentence>
        </Item>
        <Item Num="48">
          <ItemTitle>四十八</ItemTitle>
          <ItemSentence>
            <Sentence>大井川水系</Sentence>
          </ItemSentence>
        </Item>
        <Item Num="49">
          <ItemTitle>四十九</ItemTitle>
          <ItemSentence>
            <Sentence>菊川水系</Sentence>
          </ItemSentence>
        </Item>
        <Item Num="50">
          <ItemTitle>五十</ItemTitle>
          <ItemSentence>
            <Sentence>天竜川水系</Sentence>
          </ItemSentence>
        </Item>
        <Item Num="51">
          <ItemTitle>五十一</ItemTitle>
          <ItemSentence>
            <Sentence>豊川水系</Sentence>
          </ItemSentence>
        </Item>
        <Item Num="52">
          <ItemTitle>五十二</ItemTitle>
          <ItemSentence>
            <Sentence>矢作川水系</Sentence>
          </ItemSentence>
        </Item>
        <Item Num="53">
          <ItemTitle>五十三</ItemTitle>
          <ItemSentence>
            <Sentence>庄内川水系</Sentence>
          </ItemSentence>
        </Item>
        <Item Num="54">
          <ItemTitle>五十四</ItemTitle>
          <ItemSentence>
            <Sentence>木曾川水系</Sentence>
          </ItemSentence>
        </Item>
        <Item Num="55">
          <ItemTitle>五十五</ItemTitle>
          <ItemSentence>
            <Sentence>鈴鹿川水系</Sentence>
          </ItemSentence>
        </Item>
        <Item Num="56">
          <ItemTitle>五十六</ItemTitle>
          <ItemSentence>
            <Sentence>雲出川水系</Sentence>
          </ItemSentence>
        </Item>
        <Item Num="57">
          <ItemTitle>五十七</ItemTitle>
          <ItemSentence>
            <Sentence>櫛田川水系</Sentence>
          </ItemSentence>
        </Item>
        <Item Num="58">
          <ItemTitle>五十八</ItemTitle>
          <ItemSentence>
            <Sentence>宮川水系</Sentence>
          </ItemSentence>
        </Item>
        <Item Num="59">
          <ItemTitle>五十九</ItemTitle>
          <ItemSentence>
            <Sentence>由良川水系</Sentence>
          </ItemSentence>
        </Item>
        <Item Num="60">
          <ItemTitle>六十</ItemTitle>
          <ItemSentence>
            <Sentence>淀川水系</Sentence>
          </ItemSentence>
        </Item>
        <Item Num="61">
          <ItemTitle>六十一</ItemTitle>
          <ItemSentence>
            <Sentence>大和川水系</Sentence>
          </ItemSentence>
        </Item>
        <Item Num="62">
          <ItemTitle>六十二</ItemTitle>
          <ItemSentence>
            <Sentence>円山川水系</Sentence>
          </ItemSentence>
        </Item>
        <Item Num="63">
          <ItemTitle>六十三</ItemTitle>
          <ItemSentence>
            <Sentence>加古川水系</Sentence>
          </ItemSentence>
        </Item>
        <Item Num="64">
          <ItemTitle>六十四</ItemTitle>
          <ItemSentence>
            <Sentence>揖保川水系</Sentence>
          </ItemSentence>
        </Item>
        <Item Num="65">
          <ItemTitle>六十五</ItemTitle>
          <ItemSentence>
            <Sentence>紀の川水系</Sentence>
          </ItemSentence>
        </Item>
        <Item Num="66">
          <ItemTitle>六十六</ItemTitle>
          <ItemSentence>
            <Sentence>新宮川水系</Sentence>
          </ItemSentence>
        </Item>
        <Item Num="67">
          <ItemTitle>六十七</ItemTitle>
          <ItemSentence>
            <Sentence>九頭竜川水系</Sentence>
          </ItemSentence>
        </Item>
        <Item Num="68">
          <ItemTitle>六十八</ItemTitle>
          <ItemSentence>
            <Sentence>北川水系</Sentence>
          </ItemSentence>
        </Item>
        <Item Num="69">
          <ItemTitle>六十九</ItemTitle>
          <ItemSentence>
            <Sentence>千代川水系</Sentence>
          </ItemSentence>
        </Item>
        <Item Num="70">
          <ItemTitle>七十</ItemTitle>
          <ItemSentence>
            <Sentence>天神川水系</Sentence>
          </ItemSentence>
        </Item>
        <Item Num="71">
          <ItemTitle>七十一</ItemTitle>
          <ItemSentence>
            <Sentence>日野川水系</Sentence>
          </ItemSentence>
        </Item>
        <Item Num="72">
          <ItemTitle>七十二</ItemTitle>
          <ItemSentence>
            <Sentence>斐伊川水系</Sentence>
          </ItemSentence>
        </Item>
        <Item Num="73">
          <ItemTitle>七十三</ItemTitle>
          <ItemSentence>
            <Sentence>江の川水系</Sentence>
          </ItemSentence>
        </Item>
        <Item Num="74">
          <ItemTitle>七十四</ItemTitle>
          <ItemSentence>
            <Sentence>高津川水系</Sentence>
          </ItemSentence>
        </Item>
        <Item Num="75">
          <ItemTitle>七十五</ItemTitle>
          <ItemSentence>
            <Sentence>吉井川水系</Sentence>
          </ItemSentence>
        </Item>
        <Item Num="76">
          <ItemTitle>七十六</ItemTitle>
          <ItemSentence>
            <Sentence>旭川水系</Sentence>
          </ItemSentence>
        </Item>
        <Item Num="77">
          <ItemTitle>七十七</ItemTitle>
          <ItemSentence>
            <Sentence>高梁川水系</Sentence>
          </ItemSentence>
        </Item>
        <Item Num="78">
          <ItemTitle>七十八</ItemTitle>
          <ItemSentence>
            <Sentence>芦田川水系</Sentence>
          </ItemSentence>
        </Item>
        <Item Num="79">
          <ItemTitle>七十九</ItemTitle>
          <ItemSentence>
            <Sentence>太田川水系</Sentence>
          </ItemSentence>
        </Item>
        <Item Num="80">
          <ItemTitle>八十</ItemTitle>
          <ItemSentence>
            <Sentence>小瀬川水系</Sentence>
          </ItemSentence>
        </Item>
        <Item Num="81">
          <ItemTitle>八十一</ItemTitle>
          <ItemSentence>
            <Sentence>佐波川水系</Sentence>
          </ItemSentence>
        </Item>
        <Item Num="82">
          <ItemTitle>八十二</ItemTitle>
          <ItemSentence>
            <Sentence>吉野川水系</Sentence>
          </ItemSentence>
        </Item>
        <Item Num="83">
          <ItemTitle>八十三</ItemTitle>
          <ItemSentence>
            <Sentence>那賀川水系</Sentence>
          </ItemSentence>
        </Item>
        <Item Num="84">
          <ItemTitle>八十四</ItemTitle>
          <ItemSentence>
            <Sentence>土器川水系</Sentence>
          </ItemSentence>
        </Item>
        <Item Num="85">
          <ItemTitle>八十五</ItemTitle>
          <ItemSentence>
            <Sentence>重信川水系</Sentence>
          </ItemSentence>
        </Item>
        <Item Num="86">
          <ItemTitle>八十六</ItemTitle>
          <ItemSentence>
            <Sentence>肱川水系</Sentence>
          </ItemSentence>
        </Item>
        <Item Num="87">
          <ItemTitle>八十七</ItemTitle>
          <ItemSentence>
            <Sentence>物部川水系</Sentence>
          </ItemSentence>
        </Item>
        <Item Num="88">
          <ItemTitle>八十八</ItemTitle>
          <ItemSentence>
            <Sentence>仁淀川水系</Sentence>
          </ItemSentence>
        </Item>
        <Item Num="89">
          <ItemTitle>八十九</ItemTitle>
          <ItemSentence>
            <Sentence>渡川水系</Sentence>
          </ItemSentence>
        </Item>
        <Item Num="90">
          <ItemTitle>九十</ItemTitle>
          <ItemSentence>
            <Sentence>遠賀川水系</Sentence>
          </ItemSentence>
        </Item>
        <Item Num="91">
          <ItemTitle>九十一</ItemTitle>
          <ItemSentence>
            <Sentence>山国川水系</Sentence>
          </ItemSentence>
        </Item>
        <Item Num="92">
          <ItemTitle>九十二</ItemTitle>
          <ItemSentence>
            <Sentence>筑後川水系</Sentence>
          </ItemSentence>
        </Item>
        <Item Num="93">
          <ItemTitle>九十三</ItemTitle>
          <ItemSentence>
            <Sentence>矢部川水系</Sentence>
          </ItemSentence>
        </Item>
        <Item Num="94">
          <ItemTitle>九十四</ItemTitle>
          <ItemSentence>
            <Sentence>松浦川水系</Sentence>
          </ItemSentence>
        </Item>
        <Item Num="95">
          <ItemTitle>九十五</ItemTitle>
          <ItemSentence>
            <Sentence>六角川水系</Sentence>
          </ItemSentence>
        </Item>
        <Item Num="96">
          <ItemTitle>九十六</ItemTitle>
          <ItemSentence>
            <Sentence>嘉瀬川水系</Sentence>
          </ItemSentence>
        </Item>
        <Item Num="97">
          <ItemTitle>九十七</ItemTitle>
          <ItemSentence>
            <Sentence>本明川水系</Sentence>
          </ItemSentence>
        </Item>
        <Item Num="98">
          <ItemTitle>九十八</ItemTitle>
          <ItemSentence>
            <Sentence>菊池川水系</Sentence>
          </ItemSentence>
        </Item>
        <Item Num="99">
          <ItemTitle>九十九</ItemTitle>
          <ItemSentence>
            <Sentence>白川水系</Sentence>
          </ItemSentence>
        </Item>
        <Item Num="100">
          <ItemTitle>百</ItemTitle>
          <ItemSentence>
            <Sentence>緑川水系</Sentence>
          </ItemSentence>
        </Item>
        <Item Num="101">
          <ItemTitle>百一</ItemTitle>
          <ItemSentence>
            <Sentence>球磨川水系</Sentence>
          </ItemSentence>
        </Item>
        <Item Num="102">
          <ItemTitle>百二</ItemTitle>
          <ItemSentence>
            <Sentence>大分川水系</Sentence>
          </ItemSentence>
        </Item>
        <Item Num="103">
          <ItemTitle>百三</ItemTitle>
          <ItemSentence>
            <Sentence>大野川水系</Sentence>
          </ItemSentence>
        </Item>
        <Item Num="104">
          <ItemTitle>百四</ItemTitle>
          <ItemSentence>
            <Sentence>番匠川水系</Sentence>
          </ItemSentence>
        </Item>
        <Item Num="105">
          <ItemTitle>百五</ItemTitle>
          <ItemSentence>
            <Sentence>五ケ瀬川水系</Sentence>
          </ItemSentence>
        </Item>
        <Item Num="106">
          <ItemTitle>百六</ItemTitle>
          <ItemSentence>
            <Sentence>小丸川水系</Sentence>
          </ItemSentence>
        </Item>
        <Item Num="107">
          <ItemTitle>百七</ItemTitle>
          <ItemSentence>
            <Sentence>大淀川水系</Sentence>
          </ItemSentence>
        </Item>
        <Item Num="108">
          <ItemTitle>百八</ItemTitle>
          <ItemSentence>
            <Sentence>川内川水系</Sentence>
          </ItemSentence>
        </Item>
        <Item Num="109">
          <ItemTitle>百九</ItemTitle>
          <ItemSentence>
            <Sentence>肝属川水系</Sentence>
          </ItemSentence>
        </Item>
      </Paragraph>
    </MainProvision>
    <SupplProvision Extract="false" Type="New">
      <SupplProvisionLabel>附　則</SupplProvisionLabel>
      <Paragraph Num="1">
        <ParagraphNum/>
        <ParagraphSentence>
          <Sentence>この政令は、河川法の施行の日（昭和四十年四月一日）から施行する。</Sentence>
        </ParagraphSentence>
      </Paragraph>
    </SupplProvision>
    <SupplProvision AmendLawNum="昭和四一年三月二八日政令第五〇号" Type="Amend">
      <SupplProvisionLabel>附　則</SupplProvisionLabel>
      <Paragraph Num="1">
        <ParagraphNum/>
        <ParagraphSentence>
          <Sentence>この政令は、昭和四十一年四月一日から施行する。</Sentence>
        </ParagraphSentence>
      </Paragraph>
    </SupplProvision>
    <SupplProvision AmendLawNum="昭和四二年五月二五日政令第七五号" Type="Amend">
      <SupplProvisionLabel>附　則</SupplProvisionLabel>
      <Paragraph Num="1">
        <ParagraphNum/>
        <ParagraphSentence>
          <Sentence>この政令は、昭和四十二年六月一日から施行する。</Sentence>
        </ParagraphSentence>
      </Paragraph>
    </SupplProvision>
    <SupplProvision AmendLawNum="昭和四三年四月八日政令第六四号" Type="Amend">
      <SupplProvisionLabel>附　則</SupplProvisionLabel>
      <Paragraph Num="1">
        <ParagraphNum/>
        <ParagraphSentence>
          <Sentence>この政令は、昭和四十三年四月二十日から施行する。</Sentence>
        </ParagraphSentence>
      </Paragraph>
    </SupplProvision>
    <SupplProvision AmendLawNum="昭和四四年三月二〇日政令第三一号" Type="Amend">
      <SupplProvisionLabel>附　則</SupplProvisionLabel>
      <Paragraph Num="1">
        <ParagraphNum/>
        <ParagraphSentence>
          <Sentence>この政令は、昭和四十四年四月一日から施行する。</Sentence>
        </ParagraphSentence>
      </Paragraph>
    </SupplProvision>
    <SupplProvision AmendLawNum="昭和四五年三月二〇日政令第一九号" Type="Amend">
      <SupplProvisionLabel>附　則</SupplProvisionLabel>
      <Paragraph Num="1">
        <ParagraphNum/>
        <ParagraphSentence>
          <Sentence>この政令は、昭和四十五年四月一日から施行する。</Sentence>
        </ParagraphSentence>
      </Paragraph>
    </SupplProvision>
    <SupplProvision AmendLawNum="昭和四五年四月二〇日政令第八〇号" Type="Amend">
      <SupplProvisionLabel>附　則</SupplProvisionLabel>
      <Paragraph Num="1">
        <ParagraphNum/>
        <ParagraphSentence>
          <Sentence>この政令は、昭和四十五年五月一日から施行する。</Sentence>
        </ParagraphSentence>
      </Paragraph>
    </SupplProvision>
    <SupplProvision AmendLawNum="昭和四六年三月二〇日政令第二九号" Type="Amend">
      <SupplProvisionLabel>附　則</SupplProvisionLabel>
      <Paragraph Num="1">
        <ParagraphNum/>
        <ParagraphSentence>
          <Sentence>この政令は、昭和四十六年四月一日から施行する。</Sentence>
        </ParagraphSentence>
      </Paragraph>
    </SupplProvision>
    <SupplProvision AmendLawNum="昭和四七年四月二六日政令第八五号" Type="Amend">
      <SupplProvisionLabel>附　則</SupplProvisionLabel>
      <Paragraph Num="1">
        <ParagraphNum/>
        <ParagraphSentence>
          <Sentence>この政令は、昭和四十七年五月四日から施行する。</Sentence>
        </ParagraphSentence>
      </Paragraph>
    </SupplProvision>
    <SupplProvision AmendLawNum="昭和四七年九月二六日政令第三三九号" Type="Amend">
      <SupplProvisionLabel>附　則</SupplProvisionLabel>
      <Paragraph Num="1">
        <ParagraphNum/>
        <ParagraphSentence>
          <Sentence>この政令は、公布の日から施行する。</Sentence>
        </ParagraphSentence>
      </Paragraph>
    </SupplProvision>
    <SupplProvision AmendLawNum="昭和五〇年四月八日政令第一一一号" Type="Amend">
      <SupplProvisionLabel>附　則</SupplProvisionLabel>
      <Paragraph Num="1">
        <ParagraphNum/>
        <ParagraphSentence>
          <Sentence>この政令は、昭和五十年四月十二日から施行する。</Sentence>
        </ParagraphSentence>
      </Paragraph>
    </SupplProvision>
  </LawBody>
</Law>
